django_smoked-0.1_alpha.1.dist-info/DESCRIPTION.rst
django_smoked-0.1_alpha.1.dist-info/METADATA
django_smoked-0.1_alpha.1.dist-info/metadata.json
django_smoked-0.1_alpha.1.dist-info/RECORD
django_smoked-0.1_alpha.1.dist-info/top_level.txt
django_smoked-0.1_alpha.1.dist-info/WHEEL
smoked/__init__.py
smoked/apps.py
smoked/loader.py
smoked/registry.py
smoked/runner.py
smoked/urls.py
smoked/views.py
smoked/management/__init__.py
smoked/management/commands/__init__.py
smoked/management/commands/smoked.py
smoked/test/__init__.py
smoked/test/url.py
