Metadata-Version: 2.0
Name: django-smoked
Version: 0.1-alpha.1
Summary: Smoke tests framework for Django Web Framework
Home-page: https://github.com/djentlemen/django-smoked
Author: Tomáš Ehrlich
Author-email: tomas.ehrlich@gmail.com
License: MIT
Platform: UNKNOWN
Classifier: Development Status :: 2 - Pre-Alpha
Classifier: Environment :: Web Environment
Classifier: Framework :: Django
Classifier: Intended Audience :: Developers
Classifier: License :: OSI Approved :: MIT License
Classifier: Programming Language :: Python
Classifier: Programming Language :: Python :: 2
Classifier: Programming Language :: Python :: 2.6
Classifier: Programming Language :: Python :: 2.7
Classifier: Programming Language :: Python :: 3
Classifier: Programming Language :: Python :: 3.2
Classifier: Programming Language :: Python :: 3.3
Classifier: Programming Language :: Python :: 3.4
Classifier: Topic :: Software Development :: Quality Assurance
Classifier: Topic :: Software Development :: Testing
Requires-Dist: django
Provides-Extra: qa
Requires-Dist: pytest-cov; extra == 'qa'
Requires-Dist: coveralls; extra == 'qa'
Provides-Extra: tests
Requires-Dist: pytest; extra == 'tests'
Requires-Dist: pytest-django; extra == 'tests'
Requires-Dist: pytest-mock; extra == 'tests'
